{
    "0": "x",
    "id": 191,
    "parent_id": 0,
    "status": "processing",
    "currency": "USD",
    "version": "7.7.0",
    "prices_include_tax": false,
    "date_created": "2023-05-29T13:23:05",
    "date_modified": "2023-05-29T13:23:05",
    "discount_total": "0.00",
    "discount_tax": "0.00",
    "shipping_total": "0.00",
    "shipping_tax": "0.00",
    "cart_tax": "0.00",
    "total": "45.00",
    "total_tax": "0.00",
    "customer_id": 1,
    "order_key": "wc_order_Lf2bXjV4Ag9iz",
    "billing": {
        "first_name": "Jakub",
        "last_name": "Troczy\u0144ski",
        "company": "",
        "address_1": "1 MAJA",
        "address_2": "66",
        "city": "Paj\u0119czno",
        "state": "",
        "postcode": "98-330",
        "country": "PL",
        "email": "ttroczynski5@gmail.com",
        "phone": "510720673"
    },
    "shipping": {
        "first_name": "",
        "last_name": "",
        "company": "",
        "address_1": "",
        "address_2": "",
        "city": "",
        "state": "",
        "postcode": "",
        "country": "",
        "phone": ""
    },
    "payment_method": "cod",
    "payment_method_title": "Cash on delivery",
    "transaction_id": "",
    "customer_ip_address": "176.113.198.98",
    "customer_user_agent": "Mozilla\/5.0 (X11; Linux x86_64) AppleWebKit\/537.36 (KHTML, like Gecko) Chrome\/111.0.0.0 Safari\/537.36",
    "created_via": "checkout",
    "customer_note": "",
    "date_completed": null,
    "date_paid": null,
    "cart_hash": "cb7db0d971c862283d593fb07f54282c",
    "number": "191",
    "meta_data": [
        {
            "id": 6495,
            "key": "is_vat_exempt",
            "value": "no"
        },
        {
            "id": 6496,
            "key": "getreview_opinion_add",
            "value": "on"
        }
    ],
    "line_items": [
        {
            "id": 168,
            "name": "produkt1",
            "product_id": 10,
            "variation_id": 0,
            "quantity": 1,
            "tax_class": "",
            "subtotal": "45.00",
            "subtotal_tax": "0.00",
            "total": "45.00",
            "total_tax": "0.00",
            "taxes": [],
            "meta_data": [],
            "sku": "",
            "price": 45,
            "image": {
                "id": "",
                "src": ""
            },
            "parent_name": null
        }
    ],
    "tax_lines": [],
    "shipping_lines": [],
    "fee_lines": [],
    "coupon_lines": [],
    "refunds": [],
    "payment_url": "https:\/\/woo.dmn.gg\/checkout\/order-pay\/191\/?pay_for_order=true&key=wc_order_Lf2bXjV4Ag9iz",
    "is_editable": false,
    "needs_payment": false,
    "needs_processing": true,
    "date_created_gmt": "2023-05-29T11:23:05",
    "date_modified_gmt": "2023-05-29T11:23:05",
    "date_completed_gmt": null,
    "date_paid_gmt": null,
    "currency_symbol": "$",
    "_links": {
        "self": [
            {
                "href": "https:\/\/woo.dmn.gg\/wp-json\/wc\/v3\/orders\/191"
            }
        ],
        "collection": [
            {
                "href": "https:\/\/woo.dmn.gg\/wp-json\/wc\/v3\/orders"
            }
        ],
        "customer": [
            {
                "href": "https:\/\/woo.dmn.gg\/wp-json\/wc\/v3\/customers\/1"
            }
        ]
    }
}payload1234{
    "id": 191,
    "parent_id": 0,
    "status": "processing",
    "currency": "USD",
    "version": "7.7.0",
    "prices_include_tax": false,
    "date_created": "2023-05-29T13:23:05",
    "date_modified": "2023-05-29T13:23:05",
    "discount_total": "0.00",
    "discount_tax": "0.00",
    "shipping_total": "0.00",
    "shipping_tax": "0.00",
    "cart_tax": "0.00",
    "total": "45.00",
    "total_tax": "0.00",
    "customer_id": 1,
    "order_key": "wc_order_Lf2bXjV4Ag9iz",
    "billing": {
        "first_name": "Jakub",
        "last_name": "Troczy\u0144ski",
        "company": "",
        "address_1": "1 MAJA",
        "address_2": "66",
        "city": "Paj\u0119czno",
        "state": "",
        "postcode": "98-330",
        "country": "PL",
        "email": "ttroczynski5@gmail.com",
        "phone": "510720673"
    },
    "shipping": {
        "first_name": "",
        "last_name": "",
        "company": "",
        "address_1": "",
        "address_2": "",
        "city": "",
        "state": "",
        "postcode": "",
        "country": "",
        "phone": ""
    },
    "payment_method": "cod",
    "payment_method_title": "Cash on delivery",
    "transaction_id": "",
    "customer_ip_address": "176.113.198.98",
    "customer_user_agent": "Mozilla\/5.0 (X11; Linux x86_64) AppleWebKit\/537.36 (KHTML, like Gecko) Chrome\/111.0.0.0 Safari\/537.36",
    "created_via": "checkout",
    "customer_note": "",
    "date_completed": null,
    "date_paid": null,
    "cart_hash": "cb7db0d971c862283d593fb07f54282c",
    "number": "191",
    "meta_data": [
        {
            "id": 6495,
            "key": "is_vat_exempt",
            "value": "no"
        },
        {
            "id": 6496,
            "key": "getreview_opinion_add",
            "value": "on"
        }
    ],
    "line_items": [
        {
            "id": 168,
            "name": "produkt1",
            "product_id": 10,
            "variation_id": 0,
            "quantity": 1,
            "tax_class": "",
            "subtotal": "45.00",
            "subtotal_tax": "0.00",
            "total": "45.00",
            "total_tax": "0.00",
            "taxes": [],
            "meta_data": [],
            "sku": "",
            "price": 45,
            "image": {
                "id": "",
                "src": ""
            },
            "parent_name": null
        }
    ],
    "tax_lines": [],
    "shipping_lines": [],
    "fee_lines": [],
    "coupon_lines": [],
    "refunds": [],
    "payment_url": "https:\/\/woo.dmn.gg\/checkout\/order-pay\/191\/?pay_for_order=true&key=wc_order_Lf2bXjV4Ag9iz",
    "is_editable": false,
    "needs_payment": false,
    "needs_processing": true,
    "date_created_gmt": "2023-05-29T11:23:05",
    "date_modified_gmt": "2023-05-29T11:23:05",
    "date_completed_gmt": null,
    "date_paid_gmt": null,
    "currency_symbol": "$",
    "_links": {
        "self": [
            {
                "href": "https:\/\/woo.dmn.gg\/wp-json\/wc\/v3\/orders\/191"
            }
        ],
        "collection": [
            {
                "href": "https:\/\/woo.dmn.gg\/wp-json\/wc\/v3\/orders"
            }
        ],
        "customer": [
            {
                "href": "https:\/\/woo.dmn.gg\/wp-json\/wc\/v3\/customers\/1"
            }
        ]
    }
}logging1234a: 4: {s: 4: "Code";i: 418;s: 7: "Message";s: 12: "I'm a teapot";s: 7: "Headers";O: 42: "Requests_Utility_CaseInsensitiveDictionary": 1: {s: 7: "*data";a: 11: {s: 4: "date";s: 29: "Mon, 29 May 2023 11:23:11 GMT";s: 12: "content-type";s: 25: "text/plain; charset=UTF-8";s: 14: "content-length";s: 2: "12";s: 13: "cache-control";s: 17: "no-cache, private";s: 10: "set-cookie";a: 2: {i: 0;s: 342: "XSRF-TOKEN=eyJpdiI6InNcL0s5MG5rQjBYNFowM21mR3Nxc21BPT0iLCJ2YWx1ZSI6IlQ2QTgyNnVvelFGcnJzTXcxOTg4SmgwdUlVSUxBbjFcL1ZqTXpoUXA2Wm9EZ0wxRGZuV3p4eElVSFh4Y0NhVTlpIiwibWFjIjoiMjM3NmQyOTM2MDU5OTY3ZGI1NTdmMTMyZTRjOTk2MjFkMzNjZTg1MWEwN2U2NjliMjFmNTA5MDEzMmZjZmYyMyJ9; expires=Mon, 29-May-2023 13:23:11 GMT; Max-Age=7200; path=/;samesite=none;secure=true";i: 1;s: 155: "getreview_session=MgtZNRJ3AKe8mbeffZYQqATHPzhjmMYRS50wG7YX; expires=Mon, 29-May-2023 13:23:11 GMT; Max-Age=7200; path=/;samesite=none;secure=true; httponly";
            }s: 15: "cf-cache-status";s: 7: "DYNAMIC";s: 9: "report-to";s: 247: "{"endpoints":[{"url":"https:\/\/a.nel.cloudflare.com\/report\/v3?s=P2Px0zeAe7%2FMmOHkxzjWZfjAj0TKiytJZIfPIQXqdqYV%2